{
  "$schema": "https://json-schema.org/draft/2020-12/schema",
  "type": "object",
  "required": ["summary", "url", "title", "task", "keyword", "keyword_count", "headlines"],
  "properties": {
    "summary": {
      "type": "string"
    },
    "url": {
      "type": "string"
    },
    "title": {
      "type": "string"
    },
    "task": {
      "type": "string"
    },
    "highlights": {
      "type": "array",
      "items": {
        "type": "string"
      }
    },
    "headlines": {
      "type": "array",
      "items": {
        "type": "string"
      }
    },
    "keyword": {
      "type": "string"
    },
    "keyword_count": {
      "type": "integer"
    },
    "errors": {
      "type": "array"
    }
  }
}
